recentquake.py
recentquake-0.0.1.dist-info/METADATA
recentquake-0.0.1.dist-info/WHEEL
recentquake-0.0.1.dist-info/entry_points.txt
recentquake-0.0.1.dist-info/top_level.txt
recentquake-0.0.1.dist-info/RECORD
