Metadata-Version: 2.1
Name: recentquake
Version: 0.0.1
Summary: A package for visualization of the characteristics of earthquakes in the last 30 days
Home-page: https://github.com/miyagawa-toshiki/recentquake
Author: toshiki miyagawa
Author-email: s1922033@stu.musashino-u.ac.jp
License: UNKNOWN
Project-URL: Bug Tracker, https://github.com/miyagawa-toshiki/recentquake
Platform: UNKNOWN
Classifier: Programming Language :: Python :: 3
Classifier: License :: OSI Approved :: MIT License
Classifier: Operating System :: OS Independent
Requires-Python: >=3.6
